{"name":"BOING BOING CANDY HIERARCHY 2016 SURVEY Responses xlsx","tags":[],"created":"2019-10-14T08:03:28Z","modified":"2019-10-15T05:27:05Z","creator":"","contributors":"","subject":"","description":"","rowCount":1259,"title":"","homepage":"","image":"","license":"","version":"","customMetadata":{},"importOptionMetadata":[{"sheets":[{"name":"BOING-BOING-CANDY-HIERARCHY-2016-SURVEY-Responses.xlsx#Form Responses 1","fileNameAndSheetIndex":"BOING-BOING-CANDY-HIERARCHY-2016-SURVEY-Responses.xlsx#0","rows":1260,"selected":true}],"storeBlankRows":true,"skipDataLines":0,"includeFileSources":false,"headerLines":1,"limit":-1,"projectTags":[""],"ignoreLines":-1,"fileSource":"BOING-BOING-CANDY-HIERARCHY-2016-SURVEY-Responses.xlsx","projectName":"BOING BOING CANDY HIERARCHY 2016 SURVEY Responses xlsx","storeBlankCellsAsNulls":true}],"password":"","encoding":"UTF-8","encodingConfidence":0,"preferences":{"entries":{"scripting.starred-expressions":{"class":"com.google.refine.preference.TopList","top":2147483647,"list":[]},"scripting.expressions":{"class":"com.google.refine.preference.TopList","top":100,"list":[]}}}}